basicdb/.__init__.py.swp
basicdb/__init__.py
basicdb/basicdb.py
basicdb/db_adapter.py
basicdb/entities.py
basicdb/exceptions.py
basicdb/sql_adapter.py
basicdb/utils.py
basicdb-0.0.13.dist-info/WHEEL
basicdb-0.0.13.dist-info/METADATA
basicdb-0.0.13.dist-info/RECORD
